corenlp/__init__.py
corenlp/annotator.py
corenlp/client.py
corenlp/main.py
stanford_corenlp-3.9.2.dist-info/METADATA
stanford_corenlp-3.9.2.dist-info/RECORD
stanford_corenlp-3.9.2.dist-info/WHEEL
stanford_corenlp-3.9.2.dist-info/entry_points.txt
stanford_corenlp-3.9.2.dist-info/top_level.txt
