Metadata-Version: 2.1
Name: stanford-corenlp
Version: 3.9.2
Summary: Official python interface for Stanford CoreNLP
Home-page: https://github.com/stanfordnlp/python-stanford-corenlp
Author: Stanford NLP Group
Author-email: chaganty@cs.stanford.edu
License: MIT
Keywords: corenlp natural-language-processing nlp
Platform: UNKNOWN
Classifier: Development Status :: 4 - Beta
Classifier: Intended Audience :: Developers
Classifier: Topic :: Software Development :: Object Brokering
Classifier: License :: OSI Approved :: MIT License
Classifier: Programming Language :: Python :: 2
Classifier: Programming Language :: Python :: 2.7
Classifier: Programming Language :: Python :: 3
Classifier: Programming Language :: Python :: 3.3
Classifier: Programming Language :: Python :: 3.4
Classifier: Programming Language :: Python :: 3.5
Provides-Extra: dev
Provides-Extra: test
